casbin_redis_adapter/__init__.py
casbin_redis_adapter/adapter.py
casbin_redis_adapter-1.5.0.dist-info/licenses/LICENSE
tests/__init__.py
tests/test_adapter.py
casbin_redis_adapter-1.5.0.dist-info/METADATA
casbin_redis_adapter-1.5.0.dist-info/WHEEL
casbin_redis_adapter-1.5.0.dist-info/top_level.txt
casbin_redis_adapter-1.5.0.dist-info/RECORD
