Metadata-Version: 2.4
Name: casbin_redis_adapter
Version: 1.5.0
Summary: Redis Adapter for PyCasbin
Home-page: https://github.com/officialpycasbin/redis-adapter
Author: Casbin
Author-email: admin@casbin.org
License: Apache 2.0
Keywords: casbin,Redis,casbin-adapter,rbac,access control,abac,acl,permission
Classifier: Programming Language :: Python :: 3.9
Classifier: Programming Language :: Python :: 3.10
Classifier: Programming Language :: Python :: 3.11
Classifier: Programming Language :: Python :: 3.12
Classifier: License :: OSI Approved :: Apache Software License
Classifier: Operating System :: OS Independent
Requires-Python: >=3.8
License-File: LICENSE
Requires-Dist: pycasbin>=2.0.0
Requires-Dist: redis>=4.5.0
Dynamic: author
Dynamic: author-email
Dynamic: classifier
Dynamic: description
Dynamic: description-content-type
Dynamic: home-page
Dynamic: keywords
Dynamic: license
Dynamic: license-file
Dynamic: requires-dist
Dynamic: requires-python
Dynamic: summary
